msmcauthaio/__init__.py
msmcauthaio/client.py
msmcauthaio/constants.py
msmcauthaio/errors.py
msmcauthaio/http.py
msmcauthaio/models.py
msmcauthaio/helpers/__init__.py
msmcauthaio/helpers/microsoft.py
msmcauthaio/helpers/xbox.py
msmcauthaio-0.1.dist-info/LICENSE
msmcauthaio-0.1.dist-info/METADATA
msmcauthaio-0.1.dist-info/WHEEL
msmcauthaio-0.1.dist-info/top_level.txt
msmcauthaio-0.1.dist-info/RECORD
